GOESVisualizer/GOESVisualizer_mod.py
GOESVisualizer/__init__.py
GOESVisualizer/example.py
GOESVisualizer/test.py
GOESVisualizer-0.0.6.dist-info/LICENSE
GOESVisualizer-0.0.6.dist-info/METADATA
GOESVisualizer-0.0.6.dist-info/WHEEL
GOESVisualizer-0.0.6.dist-info/top_level.txt
GOESVisualizer-0.0.6.dist-info/RECORD
