Metadata-Version: 2.1
Name: GOESVisualizer
Version: 0.0.6
Summary: A simple tool to visualize GOES16/17
Author: Amir Souri
Author-email: ahsouri@gmail.com
License: MIT
License-File: LICENSE
Requires-Dist: boto3 (==1.24.28)
Requires-Dist: botocore (==1.27.28)
Requires-Dist: Cartopy (==0.21.1)
Requires-Dist: matplotlib (==3.5.2)
Requires-Dist: netCDF4 (==1.6.5)
Requires-Dist: numpy (==1.21.5)
Requires-Dist: opencv-python (==4.6.0.66)
Requires-Dist: Pillow (==10.2.0)
Requires-Dist: requests (==2.28.1)
Requires-Dist: xarray (==0.20.1)
